Metadata-Version: 2.1
Name: odoo8-addon-l10n-ch-zip
Version: 8.0.2.0.0.99.dev17
Summary: Provides all Swiss postal codes for auto-completion
Home-page: http://www.camptocamp.com
Author: Camptocamp, brain-tec AG, copadoMEDIA UG, Odoo Community Association (OCA)
Author-email: support@odoo-community.org
License: AGPL-3
Platform: UNKNOWN
Classifier: Programming Language :: Python
Classifier: Framework :: Odoo
Classifier: License :: OSI Approved :: GNU Affero General Public License v3
Requires-Python: ~=2.7
Requires-Dist: odoo8-addon-base-location
Requires-Dist: odoo8-addon-l10n-ch-states
Requires-Dist: odoo (<9.0a,>=8.0a)
